README.rst
setup.py
simpleisy/__init__.py
simpleisy.egg-info/PKG-INFO
simpleisy.egg-info/SOURCES.txt
simpleisy.egg-info/dependency_links.txt
simpleisy.egg-info/requires.txt
simpleisy.egg-info/top_level.txt