Metadata-Version: 1.0
Name: simpleisy
Version: 1.0
Summary: Python API for Universal Devices ISY994 Insteon controller
Home-page: https://github.com/cseelye/simpleisy
Author: Carl Seelye
Author-email: cseelye@gmail.com
License: MIT
Keywords: isy udi insteon
Platform: UNKNOWN
